{
  "schemaVersion": 1,
  "id": "fabricated-energistics",
  "version": "${version}",

  "name": "Fabricated Energistics",
  "description": "Big storage",
  "authors": [
    "Fudge"
  ],
  "contact": {
    "homepage": "https://github.com/natanfudge/Fabricated-Energistics",
    "sources": "https://github.com/natanfudge/Fabricated-Energistics"
  },
  "mixins":[
    "fabricated-energistics.mixins.json"
  ],
  "license": "The MIT License",
  "environment": "*",
  "entrypoints": {
    "main": [
      "fe.FabricatedEnergisticsInit"
    ],
    "client": [
      "fe.FabricatedEnergisticsClientInit"
    ]
  },
  "depends": {
    "fabricloader": ">=0.4.0",
    "fabric-language-kotlin": "*",
    "minecraft": "1.15.x"
  }
}
